Products.CMFDynamicViewFTI-7.0.3-py3.13-nspkg.pth
Products/CMFDynamicViewFTI/__init__.py
Products/CMFDynamicViewFTI/browserdefault.py
Products/CMFDynamicViewFTI/configure.zcml
Products/CMFDynamicViewFTI/content_for_tests.py
Products/CMFDynamicViewFTI/fti.py
Products/CMFDynamicViewFTI/interfaces.py
Products/CMFDynamicViewFTI/permissions.py
Products/CMFDynamicViewFTI/browser/__init__.py
Products/CMFDynamicViewFTI/browser/addWithPresettings.pt
Products/CMFDynamicViewFTI/browser/typeinfo.py
Products/CMFDynamicViewFTI/images/typeinfo.gif
Products/CMFDynamicViewFTI/profiles/sample_types/types.xml
Products/CMFDynamicViewFTI/profiles/sample_types/types/DynDocument.xml
Products/CMFDynamicViewFTI/profiles/sample_types/types/DynFolder.xml
Products/CMFDynamicViewFTI/tests/CMFDVFTITestCase.py
Products/CMFDynamicViewFTI/tests/__init__.py
Products/CMFDynamicViewFTI/tests/browserdefault.zcml
Products/CMFDynamicViewFTI/tests/test_browserdefault.py
Products/CMFDynamicViewFTI/tests/test_fti.py
products_cmfdynamicviewfti-7.0.3.dist-info/METADATA
products_cmfdynamicviewfti-7.0.3.dist-info/WHEEL
products_cmfdynamicviewfti-7.0.3.dist-info/namespace_packages.txt
products_cmfdynamicviewfti-7.0.3.dist-info/top_level.txt
products_cmfdynamicviewfti-7.0.3.dist-info/RECORD
