Metadata-Version: 2.4
Name: Products.CMFDynamicViewFTI
Version: 7.0.3
Summary: CMFDynamicViewFTI is a product for dynamic views in CMF.
Home-page: https://pypi.org/project/Products.CMFDynamicViewFTI
Author: Plone Foundation
Author-email: plone-developers@lists.sourceforge.net
License: ZPL
Keywords: Zope CMF Plone dynamic view
Classifier: Development Status :: 5 - Production/Stable
Classifier: Framework :: Plone
Classifier: Framework :: Plone :: 6.0
Classifier: Framework :: Plone :: Core
Classifier: Framework :: Zope :: 5
Classifier: License :: OSI Approved :: Zope Public License
Classifier: Programming Language :: Python
Classifier: Programming Language :: Python :: 3.8
Classifier: Programming Language :: Python :: 3.9
Classifier: Programming Language :: Python :: 3.10
Classifier: Programming Language :: Python :: 3.11
Requires-Python: >=3.8
Requires-Dist: setuptools
Requires-Dist: Products.CMFCore
Requires-Dist: Zope
Provides-Extra: test
Requires-Dist: Products.GenericSetup; extra == "test"
Requires-Dist: plone.base; extra == "test"
Requires-Dist: plone.app.testing>=4.2.5; extra == "test"
Requires-Dist: plone.testing; extra == "test"
Requires-Dist: zope.publisher; extra == "test"
Dynamic: author
Dynamic: author-email
Dynamic: classifier
Dynamic: description
Dynamic: description-content-type
Dynamic: home-page
Dynamic: keywords
Dynamic: license
Dynamic: provides-extra
Dynamic: requires-dist
Dynamic: requires-python
Dynamic: summary
